setup.py
Shivakumar_matrix_operations/__init__.py
Shivakumar_matrix_operations/check.py
Shivakumar_matrix_operations/matrix_operations.py
Shivakumar_matrix_operations.egg-info/PKG-INFO
Shivakumar_matrix_operations.egg-info/SOURCES.txt
Shivakumar_matrix_operations.egg-info/dependency_links.txt
Shivakumar_matrix_operations.egg-info/not-zip-safe
Shivakumar_matrix_operations.egg-info/requires.txt
Shivakumar_matrix_operations.egg-info/top_level.txt