Metadata-Version: 1.0
Name: Shivakumar-matrix-operations
Version: 1.2
Summary: Basic Matrix Operations
Home-page: UNKNOWN
Author: Shivakumar Valpady
Author-email: UNKNOWN
License: UNKNOWN
Platform: UNKNOWN
